readthis/__init__.py
readthis/readthis.py
readthis/data/default_text.txt
readthis-0.1.1.dist-info/LICENSE
readthis-0.1.1.dist-info/METADATA
readthis-0.1.1.dist-info/WHEEL
readthis-0.1.1.dist-info/entry_points.txt
readthis-0.1.1.dist-info/top_level.txt
readthis-0.1.1.dist-info/RECORD
