Metadata-Version: 2.1
Name: readthis
Version: 0.1.1
Summary: readthis - A command line tool to read a text file aloud
Home-page: https://github.com/entropyqueen/readthis
Author: Emy Canton
Author-email: emy.canton@proton.me
License: MIT
License-File: LICENSE
Requires-Dist: gTTS (==2.3.2)
Requires-Dist: pydub (==0.25.1)
Requires-Dist: validators (==0.20.0)
Requires-Dist: trafilatura (==1.6.1)
